{"date": "2026-07-14", "jobs": [{"id": "LinkedIn::https://www.linkedin.com/jobs/view/4439939027/", "source": "LinkedIn", "title": "Business Intelligence Analyst (Power BI) \u2013 Enterprise Data Platform", "company": "Tech One IT", "location": "United States", "link": "https://www.linkedin.com/jobs/view/4439939027/", "posted": "13 minutes ago", "easy_apply": false, "region": "Remote - United States", "found_at": "2026-07-14T22:37:12.623017+00:00"}, {"id": "LinkedIn::https://www.linkedin.com/jobs/view/4440838842/", "source": "LinkedIn", "title": "Data Science Account Manager", "company": "Gateworx", "location": "Cairo, Egypt", "link": "https://www.linkedin.com/jobs/view/4440838842/", "posted": "14 minutes ago", "easy_apply": false, "region": "Egypt", "found_at": "2026-07-14T22:03:12.788561+00:00"}, {"id": "LinkedIn::https://www.linkedin.com/jobs/view/4440804460/", "source": "LinkedIn", "title": "Business Analyst, Product", "company": "Nearmap", "location": "Lehi, UT", "link": "https://www.linkedin.com/jobs/view/4440804460/", "posted": "3 hours ago", "easy_apply": false, "region": "Remote - United States", "found_at": "2026-07-14T22:06:47.932784+00:00"}, {"id": "LinkedIn::https://www.linkedin.com/jobs/view/4440844579/", "source": "LinkedIn", "title": "Data Analyst", "company": "Resource Innovations", "location": "St Louis, MO", "link": "https://www.linkedin.com/jobs/view/4440844579/", "posted": "32 minutes ago", "easy_apply": false, "region": "Remote - United States", "found_at": "2026-07-14T22:06:50.185076+00:00"}, {"id": "LinkedIn::https://www.linkedin.com/jobs/view/4437699221/", "source": "LinkedIn", "title": "Mid/Senior Data Engineer", "company": "Pegasus Knowledge Solutions, Inc.", "location": "New York, United States", "link": "https://www.linkedin.com/jobs/view/4437699221/", "posted": "6 hours ago", "easy_apply": false, "region": "Remote - United States", "found_at": "2026-07-14T22:06:56.155485+00:00"}, {"id": "LinkedIn::https://www.linkedin.com/jobs/view/4440831692/", "source": "LinkedIn", "title": "Healthcare Reporting Analyst", "company": "TurningPoint Healthcare Solutions", "location": "Florida, United States", "link": "https://www.linkedin.com/jobs/view/4440831692/", "posted": "21 hours ago", "easy_apply": false, "region": "Remote - United States", "found_at": "2026-07-14T21:06:44.384775+00:00"}, {"id": "LinkedIn::https://www.linkedin.com/jobs/view/4439467586/", "source": "LinkedIn", "title": "Senior Analytics Engineer (SAS to Python Modernization)", "company": "Techgene Solutions", "location": "United States", "link": "https://www.linkedin.com/jobs/view/4439467586/", "posted": "23 hours ago", "easy_apply": false, "region": "Remote - United States", "found_at": "2026-07-14T21:06:49.896735+00:00"}, {"id": "LinkedIn::https://www.linkedin.com/jobs/view/4438017520/", "source": "LinkedIn", "title": "Data Analyst", "company": "Haystack", "location": "Washington, DC", "link": "https://www.linkedin.com/jobs/view/4438017520/", "posted": "40 minutes ago", "easy_apply": false, "region": "Remote - United States", "found_at": "2026-07-14T20:36:48.993768+00:00"}, {"id": "LinkedIn::https://www.linkedin.com/jobs/view/4439917349/", "source": "LinkedIn", "title": "Business Intelligence  Analyst", "company": "Blitzin Services", "location": "United States", "link": "https://www.linkedin.com/jobs/view/4439917349/", "posted": "35 minutes ago", "easy_apply": false, "region": "Remote - United States", "found_at": "2026-07-14T20:36:53.644029+00:00"}, {"id": "LinkedIn::https://www.linkedin.com/jobs/view/4439924099/", "source": "LinkedIn", "title": "Data Engineer \u2013 Power BI", "company": "Envision Technology Solutions", "location": "United States", "link": "https://www.linkedin.com/jobs/view/4439924099/", "posted": "22 minutes ago", "easy_apply": false, "region": "Remote - United States", "found_at": "2026-07-14T20:36:57.428929+00:00"}, {"id": "LinkedIn::https://www.linkedin.com/jobs/view/4440823877/", "source": "LinkedIn", "title": "Power BI Report Developer", "company": "CGI", "location": "United States", "link": "https://www.linkedin.com/jobs/view/4440823877/", "posted": "14 minutes ago", "easy_apply": false, "region": "Remote - United States", "found_at": "2026-07-14T20:36:57.429698+00:00"}, {"id": "LinkedIn::https://www.linkedin.com/jobs/view/4400867335/", "source": "LinkedIn", "title": "Associate, Data Analytics (Atlanta, GA- Remote)", "company": "Oscar Health", "location": "United States", "link": "https://www.linkedin.com/jobs/view/4400867335/", "posted": "6 hours ago", "easy_apply": false, "region": "Remote - United States", "found_at": "2026-07-14T20:06:54.527259+00:00"}, {"id": "LinkedIn::https://www.linkedin.com/jobs/view/4440824442/", "source": "LinkedIn", "title": "Data Insights Analys -  (Remote, Entry-Level)", "company": "J\u00f3venes en LinkedIn", "location": "United States", "link": "https://www.linkedin.com/jobs/view/4440824442/", "posted": "31 minutes ago", "easy_apply": false, "region": "Remote - United States", "found_at": "2026-07-14T20:07:02.054258+00:00"}, {"id": "LinkedIn::https://www.linkedin.com/jobs/view/4438662530/", "source": "LinkedIn", "title": "Analytics Engineer \u2013 Marketing Data Warehouse: 26-01563", "company": "Akraya, Inc.", "location": "California, United States", "link": "https://www.linkedin.com/jobs/view/4438662530/", "posted": "17 minutes ago", "easy_apply": false, "region": "Remote - United States", "found_at": "2026-07-14T20:07:07.268132+00:00"}, {"id": "LinkedIn::https://www.linkedin.com/jobs/view/4440377260/", "source": "LinkedIn", "title": "Business Analyst, Analytics", "company": "Meduvi", "location": "United States", "link": "https://www.linkedin.com/jobs/view/4440377260/", "posted": "17 hours ago", "easy_apply": false, "region": "Remote - United States", "found_at": "2026-07-14T19:06:33.129867+00:00"}, {"id": "LinkedIn::https://www.linkedin.com/jobs/view/4439904223/", "source": "LinkedIn", "title": "Senior Business Analyst", "company": "Endava", "location": "United States", "link": "https://www.linkedin.com/jobs/view/4439904223/", "posted": "9 minutes ago", "easy_apply": false, "region": "Remote - United States", "found_at": "2026-07-14T19:06:34.797577+00:00"}, {"id": "LinkedIn::https://www.linkedin.com/jobs/view/4440504147/", "source": "LinkedIn", "title": "Expert Opportunity - Business Analyst ($100/hr, up to $2,000/week)", "company": "Ethos", "location": "Chicago, IL", "link": "https://www.linkedin.com/jobs/view/4440504147/", "posted": "13 hours ago", "easy_apply": false, "region": "Remote - United States", "found_at": "2026-07-14T19:06:37.054334+00:00"}, {"id": "LinkedIn::https://www.linkedin.com/jobs/view/4439893277/", "source": "LinkedIn", "title": "Business Analyst", "company": "Morae", "location": "United States", "link": "https://www.linkedin.com/jobs/view/4439893277/", "posted": "2 hours ago", "easy_apply": false, "region": "Remote - United States", "found_at": "2026-07-14T19:06:37.054607+00:00"}, {"id": "LinkedIn::https://www.linkedin.com/jobs/view/4438003682/", "source": "LinkedIn", "title": "Data Analyst", "company": "IDC", "location": "Cairo, Cairo, Egypt", "link": "https://www.linkedin.com/jobs/view/4438003682/", "posted": "7 minutes ago", "easy_apply": false, "region": "Egypt", "found_at": "2026-07-14T18:30:33.166224+00:00"}, {"id": "LinkedIn::https://www.linkedin.com/jobs/view/4440098186/", "source": "LinkedIn", "title": "Business Analyst- Medicaid", "company": "CSG Government Solutions", "location": "United States", "link": "https://www.linkedin.com/jobs/view/4440098186/", "posted": "23 hours ago", "easy_apply": false, "region": "Remote - United States", "found_at": "2026-07-14T18:36:59.640645+00:00"}, {"id": "LinkedIn::https://www.linkedin.com/jobs/view/4440599397/", "source": "LinkedIn", "title": "Staff Analytics Engineer", "company": "Toast", "location": "United States", "link": "https://www.linkedin.com/jobs/view/4440599397/", "posted": "29 minutes ago", "easy_apply": false, "region": "Remote - United States", "found_at": "2026-07-14T18:37:03.185681+00:00"}, {"id": "LinkedIn::https://www.linkedin.com/jobs/view/4421873218/", "source": "LinkedIn", "title": "Senior Data Engineer", "company": "Arrow Electronics", "location": "Cairo, Cairo, Egypt", "link": "https://www.linkedin.com/jobs/view/4421873218/", "posted": "51 minutes ago", "easy_apply": false, "region": "Egypt", "found_at": "2026-07-14T18:03:34.155831+00:00"}, {"id": "LinkedIn::https://www.linkedin.com/jobs/view/4427385740/", "source": "LinkedIn", "title": "Operational Data Analyst", "company": "Nabla", "location": "New York City Metropolitan Area", "link": "https://www.linkedin.com/jobs/view/4427385740/", "posted": "7 hours ago", "easy_apply": false, "region": "Remote - United States", "found_at": "2026-07-14T18:06:33.768623+00:00"}, {"id": "LinkedIn::https://www.linkedin.com/jobs/view/4439894520/", "source": "LinkedIn", "title": "Data Analytics AI & Tools Officer (PMO)", "company": "Schneider Electric", "location": "Egypt", "link": "https://www.linkedin.com/jobs/view/4439894520/", "posted": "16 minutes ago", "easy_apply": false, "region": "Egypt", "found_at": "2026-07-14T17:31:07.873943+00:00"}, {"id": "LinkedIn::https://www.linkedin.com/jobs/view/4439884636/", "source": "LinkedIn", "title": "Data Analytics AI & Tools Officer (PMO)", "company": "Schneider Electric", "location": "Cairo, Cairo, Egypt", "link": "https://www.linkedin.com/jobs/view/4439884636/", "posted": "22 minutes ago", "easy_apply": false, "region": "Egypt", "found_at": "2026-07-14T17:32:55.532084+00:00"}, {"id": "LinkedIn::https://www.linkedin.com/jobs/view/4440579471/", "source": "LinkedIn", "title": "Azure Data Engineer  AI & Data Platform", "company": "Avanciers Inc.", "location": "United States", "link": "https://www.linkedin.com/jobs/view/4440579471/", "posted": "1 hour ago", "easy_apply": false, "region": "Remote - United States", "found_at": "2026-07-14T17:37:04.331152+00:00"}, {"id": "LinkedIn::https://www.linkedin.com/jobs/view/4439875944/", "source": "LinkedIn", "title": "Senior BI Analyst", "company": "ARRISE", "location": "United States", "link": "https://www.linkedin.com/jobs/view/4439875944/", "posted": "7 minutes ago", "easy_apply": false, "region": "Remote - United States", "found_at": "2026-07-14T17:06:53.396504+00:00"}, {"id": "LinkedIn::https://www.linkedin.com/jobs/view/4440395457/", "source": "LinkedIn", "title": "Expert Opportunity - Business Analyst ($100/hr, up to $2,000/week)", "company": "Ethos", "location": "Boston, MA", "link": "https://www.linkedin.com/jobs/view/4440395457/", "posted": "11 hours ago", "easy_apply": false, "region": "Remote - United States", "found_at": "2026-07-14T17:06:58.020576+00:00"}, {"id": "LinkedIn::https://www.linkedin.com/jobs/view/4437087653/", "source": "LinkedIn", "title": "Business Data Analyst", "company": "Healthcare IS", "location": "United States", "link": "https://www.linkedin.com/jobs/view/4437087653/", "posted": "10 minutes ago", "easy_apply": false, "region": "Remote - United States", "found_at": "2026-07-14T16:36:37.256578+00:00"}, {"id": "LinkedIn::https://www.linkedin.com/jobs/view/4419285818/", "source": "LinkedIn", "title": "Data Engineer-Data Platforms-Databricks", "company": "IBM", "location": "Giza, Al Jizah, Egypt", "link": "https://www.linkedin.com/jobs/view/4419285818/", "posted": "3 minutes ago", "easy_apply": false, "region": "Egypt", "found_at": "2026-07-14T16:00:29.379377+00:00"}, {"id": "LinkedIn::https://www.linkedin.com/jobs/view/4437685969/", "source": "LinkedIn", "title": "Power BI and Azure web developer", "company": "Mastech Digital", "location": "United States", "link": "https://www.linkedin.com/jobs/view/4437685969/", "posted": "34 minutes ago", "easy_apply": false, "region": "Remote - United States", "found_at": "2026-07-14T16:06:48.972534+00:00"}, {"id": "LinkedIn::https://www.linkedin.com/jobs/view/4437666028/", "source": "LinkedIn", "title": "Data Analyst", "company": "Haystack", "location": "United States", "link": "https://www.linkedin.com/jobs/view/4437666028/", "posted": "7 hours ago", "easy_apply": false, "region": "Remote - United States", "found_at": "2026-07-14T15:36:55.257000+00:00"}, {"id": "LinkedIn::https://www.linkedin.com/jobs/view/4439870625/", "source": "LinkedIn", "title": "Business Intelligence Analyst with Microsoft Fabric", "company": "Hallmark Global Solutions Ltd", "location": "United States", "link": "https://www.linkedin.com/jobs/view/4439870625/", "posted": "10 minutes ago", "easy_apply": false, "region": "Remote - United States", "found_at": "2026-07-14T15:06:45.715364+00:00"}, {"id": "LinkedIn::https://www.linkedin.com/jobs/view/4437693461/", "source": "LinkedIn", "title": "Senior BI / Data Warehouse Engineer (SQL Server, SSAS, Cognos)", "company": "ABCloudz", "location": "United States", "link": "https://www.linkedin.com/jobs/view/4437693461/", "posted": "42 minutes ago", "easy_apply": false, "region": "Remote - United States", "found_at": "2026-07-14T15:06:49.581368+00:00"}, {"id": "LinkedIn::https://www.linkedin.com/jobs/view/4439873189/", "source": "LinkedIn", "title": "Senior Business Analyst", "company": "Precision Technologies", "location": "Texas, United States", "link": "https://www.linkedin.com/jobs/view/4439873189/", "posted": "54 minutes ago", "easy_apply": false, "region": "Remote - United States", "found_at": "2026-07-14T15:06:52.067801+00:00"}, {"id": "LinkedIn::https://www.linkedin.com/jobs/view/4437696112/", "source": "LinkedIn", "title": "Analytics Engineer", "company": "CodeVertex System", "location": "United States", "link": "https://www.linkedin.com/jobs/view/4437696112/", "posted": "1 hour ago", "easy_apply": false, "region": "Remote - United States", "found_at": "2026-07-14T15:06:54.288138+00:00"}, {"id": "LinkedIn::https://www.linkedin.com/jobs/view/4439860672/", "source": "LinkedIn", "title": "Senior Business Analyst", "company": "Nexttec Technology Outsourcing", "location": "Cairo, Cairo, Egypt", "link": "https://www.linkedin.com/jobs/view/4439860672/", "posted": "10 minutes ago", "easy_apply": false, "region": "Egypt", "found_at": "2026-07-14T14:30:42.445811+00:00"}, {"id": "LinkedIn::https://www.linkedin.com/jobs/view/4440576074/", "source": "LinkedIn", "title": "Data Management Consultant- Riyadh, KSA", "company": "DeepSource Technologies", "location": "Cairo, Cairo, Egypt", "link": "https://www.linkedin.com/jobs/view/4440576074/", "posted": "5 minutes ago", "easy_apply": false, "region": "Egypt", "found_at": "2026-07-14T14:33:55.853621+00:00"}, {"id": "LinkedIn::https://www.linkedin.com/jobs/view/4437647994/", "source": "LinkedIn", "title": "Data Analyst", "company": "Haystack", "location": "Los Angeles, CA", "link": "https://www.linkedin.com/jobs/view/4437647994/", "posted": "6 hours ago", "easy_apply": false, "region": "Remote - United States", "found_at": "2026-07-14T14:37:14.394834+00:00"}, {"id": "LinkedIn::https://www.linkedin.com/jobs/view/4439866487/", "source": "LinkedIn", "title": "Business Intelligence  Analyst", "company": "Klyra", "location": "United States", "link": "https://www.linkedin.com/jobs/view/4439866487/", "posted": "22 minutes ago", "easy_apply": false, "region": "Remote - United States", "found_at": "2026-07-14T14:37:18.003524+00:00"}, {"id": "LinkedIn::https://www.linkedin.com/jobs/view/4437678866/", "source": "LinkedIn", "title": "Senior Data Analyst (Tableau, AI, and Slack-based reporting)", "company": "Kani Solutions Inc", "location": "United States", "link": "https://www.linkedin.com/jobs/view/4437678866/", "posted": "29 minutes ago", "easy_apply": false, "region": "Remote - United States", "found_at": "2026-07-14T14:37:18.004336+00:00"}, {"id": "LinkedIn::https://www.linkedin.com/jobs/view/4440555794/", "source": "LinkedIn", "title": "Data Analyst - Prepit", "company": "Dsquares", "location": "6th of October, Cairo, Egypt", "link": "https://www.linkedin.com/jobs/view/4440555794/", "posted": "26 minutes ago", "easy_apply": false, "region": "Egypt", "found_at": "2026-07-14T14:00:33.783652+00:00"}, {"id": "LinkedIn::https://www.linkedin.com/jobs/view/4431712042/", "source": "LinkedIn", "title": "Assistant Manager - BI.Egypt-MIS-HO.International Banking Group", "company": "Mashreq", "location": "Egypt", "link": "https://www.linkedin.com/jobs/view/4431712042/", "posted": "22 minutes ago", "easy_apply": false, "region": "Egypt", "found_at": "2026-07-14T14:00:33.783994+00:00"}, {"id": "LinkedIn::https://www.linkedin.com/jobs/view/4437693252/", "source": "LinkedIn", "title": "SENIOR DATA ENGINEER", "company": "Atos", "location": "Cairo, Cairo, Egypt", "link": "https://www.linkedin.com/jobs/view/4437693252/", "posted": "13 minutes ago", "easy_apply": false, "region": "Egypt", "found_at": "2026-07-14T14:06:07.720818+00:00"}, {"id": "LinkedIn::https://www.linkedin.com/jobs/view/4440556808/", "source": "LinkedIn", "title": "Junior Data Analyst", "company": "Helic & Co", "location": "United States", "link": "https://www.linkedin.com/jobs/view/4440556808/", "posted": "11 minutes ago", "easy_apply": false, "region": "Remote - United States", "found_at": "2026-07-14T14:06:51.389698+00:00"}, {"id": "LinkedIn::https://www.linkedin.com/jobs/view/4437667021/", "source": "LinkedIn", "title": "Data Analyst", "company": "Haystack", "location": "Portland, OR", "link": "https://www.linkedin.com/jobs/view/4437667021/", "posted": "6 hours ago", "easy_apply": false, "region": "Remote - United States", "found_at": "2026-07-14T14:06:51.390740+00:00"}, {"id": "LinkedIn::https://www.linkedin.com/jobs/view/4439866329/", "source": "LinkedIn", "title": "Data Engineer", "company": "RAIS USA", "location": "United States", "link": "https://www.linkedin.com/jobs/view/4439866329/", "posted": "39 minutes ago", "easy_apply": false, "region": "Remote - United States", "found_at": "2026-07-14T14:07:01.889621+00:00"}, {"id": "LinkedIn::https://www.linkedin.com/jobs/view/4437669039/", "source": "LinkedIn", "title": "Data Analyst", "company": "Haystack", "location": "California, United States", "link": "https://www.linkedin.com/jobs/view/4437669039/", "posted": "5 hours ago", "easy_apply": false, "region": "Remote - United States", "found_at": "2026-07-14T13:36:32.166803+00:00"}, {"id": "LinkedIn::https://www.linkedin.com/jobs/view/4437678615/", "source": "LinkedIn", "title": "Business Intelligence Analyst", "company": "CodeVertex Innovations", "location": "United States", "link": "https://www.linkedin.com/jobs/view/4437678615/", "posted": "26 minutes ago", "easy_apply": false, "region": "Remote - United States", "found_at": "2026-07-14T13:36:35.454264+00:00"}, {"id": "LinkedIn::https://www.linkedin.com/jobs/view/4437680513/", "source": "LinkedIn", "title": "Business Intelligence Analyst", "company": "CodeVertex Innovations", "location": "United States", "link": "https://www.linkedin.com/jobs/view/4437680513/", "posted": "26 minutes ago", "easy_apply": false, "region": "Remote - United States", "found_at": "2026-07-14T13:36:35.454716+00:00"}, {"id": "LinkedIn::https://www.linkedin.com/jobs/view/4437684423/", "source": "LinkedIn", "title": "Business Intelligence Analyst", "company": "CodeVertex Innovations", "location": "United States", "link": "https://www.linkedin.com/jobs/view/4437684423/", "posted": "26 minutes ago", "easy_apply": false, "region": "Remote - United States", "found_at": "2026-07-14T13:36:35.454863+00:00"}, {"id": "LinkedIn::https://www.linkedin.com/jobs/view/4440317906/", "source": "LinkedIn", "title": "Data Analyst", "company": "GForce Life Sciences", "location": "New Jersey, United States", "link": "https://www.linkedin.com/jobs/view/4440317906/", "posted": "15 hours ago", "easy_apply": false, "region": "Remote - United States", "found_at": "2026-07-14T13:36:40.811713+00:00"}, {"id": "LinkedIn::https://www.linkedin.com/jobs/view/4437686314/", "source": "LinkedIn", "title": "Business Analyst", "company": "Impelsys", "location": "United States", "link": "https://www.linkedin.com/jobs/view/4437686314/", "posted": "16 minutes ago", "easy_apply": false, "region": "Remote - United States", "found_at": "2026-07-14T13:36:44.102411+00:00"}, {"id": "LinkedIn::https://www.linkedin.com/jobs/view/4439859286/", "source": "LinkedIn", "title": "Data Engineer", "company": "RAIS USA", "location": "United States", "link": "https://www.linkedin.com/jobs/view/4439859286/", "posted": "52 minutes ago", "easy_apply": false, "region": "Remote - United States", "found_at": "2026-07-14T13:36:47.140029+00:00"}, {"id": "LinkedIn::https://www.linkedin.com/jobs/view/4432227778/", "source": "LinkedIn", "title": "Analytics Engineer II", "company": "talabat", "location": "Cairo, Cairo, Egypt", "link": "https://www.linkedin.com/jobs/view/4432227778/", "posted": "1 minute ago", "easy_apply": false, "region": "Egypt", "found_at": "2026-07-14T13:01:28.886750+00:00"}, {"id": "LinkedIn::https://www.linkedin.com/jobs/view/4440542055/", "source": "LinkedIn", "title": "Business Data Analyst", "company": "Sundayy", "location": "United States", "link": "https://www.linkedin.com/jobs/view/4440542055/", "posted": "2 hours ago", "easy_apply": false, "region": "Remote - United States", "found_at": "2026-07-14T13:06:42.985200+00:00"}, {"id": "LinkedIn::https://www.linkedin.com/jobs/view/4439842048/", "source": "LinkedIn", "title": "Lead Business Analyst - Data Analysis,", "company": "Pinnacle Method Consulting", "location": "United States", "link": "https://www.linkedin.com/jobs/view/4439842048/", "posted": "5 hours ago", "easy_apply": false, "region": "Remote - United States", "found_at": "2026-07-14T13:06:46.389144+00:00"}, {"id": "LinkedIn::https://www.linkedin.com/jobs/view/4440552464/", "source": "LinkedIn", "title": "PowerBI Engineer", "company": "New York Technology Partners", "location": "Chicago, IL", "link": "https://www.linkedin.com/jobs/view/4440552464/", "posted": "12 minutes ago", "easy_apply": false, "region": "Remote - United States", "found_at": "2026-07-14T13:06:49.334874+00:00"}, {"id": "LinkedIn::https://www.linkedin.com/jobs/view/4440532453/", "source": "LinkedIn", "title": "Business Analyst - Remote", "company": "Sundayy", "location": "United States", "link": "https://www.linkedin.com/jobs/view/4440532453/", "posted": "2 hours ago", "easy_apply": false, "region": "Remote - United States", "found_at": "2026-07-14T13:06:51.154954+00:00"}, {"id": "LinkedIn::https://www.linkedin.com/jobs/view/4421879949/", "source": "LinkedIn", "title": "Data Engineer I", "company": "Teamworks", "location": "United States", "link": "https://www.linkedin.com/jobs/view/4421879949/", "posted": "3 minutes ago", "easy_apply": false, "region": "Remote - United States", "found_at": "2026-07-14T13:06:54.224160+00:00"}, {"id": "LinkedIn::https://www.linkedin.com/jobs/view/4439853400/", "source": "LinkedIn", "title": "Warehouse Data Coordinator", "company": "talabat", "location": "Cairo, Cairo, Egypt", "link": "https://www.linkedin.com/jobs/view/4439853400/", "posted": "1 minute ago", "easy_apply": false, "region": "Egypt", "found_at": "2026-07-14T12:33:39.382493+00:00"}, {"id": "LinkedIn::https://www.linkedin.com/jobs/view/4440507047/", "source": "LinkedIn", "title": "Expert Opportunity - Business Analyst ($100/hr, up to $2,000/week)", "company": "Ethos", "location": "United States", "link": "https://www.linkedin.com/jobs/view/4440507047/", "posted": "6 hours ago", "easy_apply": false, "region": "Remote - United States", "found_at": "2026-07-14T12:06:59.914424+00:00"}, {"id": "LinkedIn::https://www.linkedin.com/jobs/view/4437663870/", "source": "LinkedIn", "title": "Senior Data Science Consultant \u2013 Cards Marketing Analytics", "company": "Hiresquad Resources", "location": "Cairo, Egypt", "link": "https://www.linkedin.com/jobs/view/4437663870/", "posted": "2 minutes ago", "easy_apply": false, "region": "Egypt", "found_at": "2026-07-14T11:31:45.384843+00:00"}, {"id": "LinkedIn::https://www.linkedin.com/jobs/view/4440520835/", "source": "LinkedIn", "title": "Data Science Lead (Proptech)", "company": "\u062f\u0648\u064a\u0644\u064a\u0648 | Dwelleo", "location": "Egypt", "link": "https://www.linkedin.com/jobs/view/4440520835/", "posted": "26 minutes ago", "easy_apply": false, "region": "Egypt", "found_at": "2026-07-14T11:01:44.162929+00:00"}, {"id": "LinkedIn::https://www.linkedin.com/jobs/view/4440500285/", "source": "LinkedIn", "title": "Expert Opportunity - Business Analyst ($100/hr, up to $2,000/week)", "company": "Ethos", "location": "New York, NY", "link": "https://www.linkedin.com/jobs/view/4440500285/", "posted": "5 hours ago", "easy_apply": false, "region": "Remote - United States", "found_at": "2026-07-14T10:36:57.630629+00:00"}, {"id": "LinkedIn::https://www.linkedin.com/jobs/view/4429419898/", "source": "LinkedIn", "title": "Analytics Engineer 5 - Ads Measurement DSE", "company": "Netflix", "location": "United States", "link": "https://www.linkedin.com/jobs/view/4429419898/", "posted": "22 minutes ago", "easy_apply": false, "region": "Remote - United States", "found_at": "2026-07-14T10:36:59.436767+00:00"}, {"id": "LinkedIn::https://www.linkedin.com/jobs/view/4440089289/", "source": "LinkedIn", "title": "Business Analyst", "company": "Solugenix", "location": "South Carolina, United States", "link": "https://www.linkedin.com/jobs/view/4440089289/", "posted": "15 hours ago", "easy_apply": false, "region": "Remote - United States", "found_at": "2026-07-14T10:07:05.856281+00:00"}, {"id": "LinkedIn::https://www.linkedin.com/jobs/view/4437665486/", "source": "LinkedIn", "title": "Business Analyst (Technical)", "company": "Ulemt", "location": "Cairo, Cairo, Egypt", "link": "https://www.linkedin.com/jobs/view/4437665486/", "posted": "9 minutes ago", "easy_apply": false, "region": "Egypt", "found_at": "2026-07-14T09:30:34.351368+00:00"}, {"id": "LinkedIn::https://www.linkedin.com/jobs/view/4440531185/", "source": "LinkedIn", "title": "Senior Data Engineer", "company": "Sana Commerce", "location": "Alexandria, Egypt", "link": "https://www.linkedin.com/jobs/view/4440531185/", "posted": "1 minute ago", "easy_apply": false, "region": "Egypt", "found_at": "2026-07-14T09:35:04.858636+00:00"}, {"id": "LinkedIn::https://www.linkedin.com/jobs/view/4440515902/", "source": "LinkedIn", "title": "Senior Data Engineer - Alexandria", "company": "Sana Commerce", "location": "Alexandria, Alexandria, Egypt", "link": "https://www.linkedin.com/jobs/view/4440515902/", "posted": "2 minutes ago", "easy_apply": false, "region": "Egypt", "found_at": "2026-07-14T09:35:04.858848+00:00"}, {"id": "LinkedIn::https://www.linkedin.com/jobs/view/4437651510/", "source": "LinkedIn", "title": "Data Analyst", "company": "Haystack", "location": "United States", "link": "https://www.linkedin.com/jobs/view/4437651510/", "posted": "1 hour ago", "easy_apply": false, "region": "Remote - United States", "found_at": "2026-07-14T09:36:28.802555+00:00"}, {"id": "LinkedIn::https://www.linkedin.com/jobs/view/4437665401/", "source": "LinkedIn", "title": "Senior Business Intelligence Engineer", "company": "quTIP", "location": "Cairo, Egypt", "link": "https://www.linkedin.com/jobs/view/4437665401/", "posted": "4 minutes ago", "easy_apply": false, "region": "Egypt", "found_at": "2026-07-14T09:00:40.713491+00:00"}, {"id": "LinkedIn::https://www.linkedin.com/jobs/view/4437651508/", "source": "LinkedIn", "title": "Data Analyst", "company": "Haystack", "location": "New York, United States", "link": "https://www.linkedin.com/jobs/view/4437651508/", "posted": "1 hour ago", "easy_apply": false, "region": "Remote - United States", "found_at": "2026-07-14T09:06:39.723942+00:00"}, {"id": "LinkedIn::https://www.linkedin.com/jobs/view/4437662184/", "source": "LinkedIn", "title": "Junior Data Analyst", "company": "Haystack", "location": "United States", "link": "https://www.linkedin.com/jobs/view/4437662184/", "posted": "11 minutes ago", "easy_apply": false, "region": "Remote - United States", "found_at": "2026-07-14T08:06:36.540637+00:00"}, {"id": "LinkedIn::https://www.linkedin.com/jobs/view/4437640706/", "source": "LinkedIn", "title": "Data Analyst Intern", "company": "Stealth", "location": "United States", "link": "https://www.linkedin.com/jobs/view/4437640706/", "posted": "2 hours ago", "easy_apply": false, "region": "Remote - United States", "found_at": "2026-07-14T07:36:25.673307+00:00"}, {"id": "LinkedIn::https://www.linkedin.com/jobs/view/4439142639/", "source": "LinkedIn", "title": "Data Analyst", "company": "Haystack", "location": "Washington DC-Baltimore Area", "link": "https://www.linkedin.com/jobs/view/4439142639/", "posted": "23 hours ago", "easy_apply": false, "region": "Remote - United States", "found_at": "2026-07-14T07:36:25.673454+00:00"}, {"id": "LinkedIn::https://www.linkedin.com/jobs/view/4439432944/", "source": "LinkedIn", "title": "Data Analyst", "company": "Medasource", "location": "United States", "link": "https://www.linkedin.com/jobs/view/4439432944/", "posted": "13 hours ago", "easy_apply": false, "region": "Remote - United States", "found_at": "2026-07-14T07:36:25.673615+00:00"}, {"id": "LinkedIn::https://www.linkedin.com/jobs/view/4440513263/", "source": "LinkedIn", "title": "Business Analyst", "company": "Talaat Moustafa Group", "location": "Cairo, Cairo, Egypt", "link": "https://www.linkedin.com/jobs/view/4440513263/", "posted": "2 minutes ago", "easy_apply": false, "region": "Egypt", "found_at": "2026-07-14T07:05:36.461570+00:00"}, {"id": "LinkedIn::https://www.linkedin.com/jobs/view/4437641709/", "source": "LinkedIn", "title": "Data Engineer & ML Developer", "company": "Genia Big Data", "location": "United States", "link": "https://www.linkedin.com/jobs/view/4437641709/", "posted": "1 hour ago", "easy_apply": false, "region": "Remote - United States", "found_at": "2026-07-14T06:36:37.506116+00:00"}, {"id": "LinkedIn::https://www.linkedin.com/jobs/view/4440502311/", "source": "LinkedIn", "title": "Excel Analyst (Remote)", "company": "Quik Hire Staffing", "location": "United Arab Emirates", "link": "https://www.linkedin.com/jobs/view/4440502311/", "posted": "36 minutes ago", "easy_apply": false, "region": "Remote - United Arab Emirates", "found_at": "2026-07-14T06:07:17.949777+00:00"}, {"id": "LinkedIn::https://www.linkedin.com/jobs/view/4440500365/", "source": "LinkedIn", "title": "Business Intelligence Consultant (Remote)", "company": "Quik Hire Staffing", "location": "United Arab Emirates", "link": "https://www.linkedin.com/jobs/view/4440500365/", "posted": "36 minutes ago", "easy_apply": false, "region": "Remote - United Arab Emirates", "found_at": "2026-07-14T06:07:20.516870+00:00"}, {"id": "LinkedIn::https://www.linkedin.com/jobs/view/4440386924/", "source": "LinkedIn", "title": "Data Analyst - Business (Remote)", "company": "Hire Feed", "location": "Egypt", "link": "https://www.linkedin.com/jobs/view/4440386924/", "posted": "12 minutes ago", "easy_apply": false, "region": "Egypt", "found_at": "2026-07-14T05:30:29.824781+00:00"}, {"id": "LinkedIn::https://www.linkedin.com/jobs/view/4440500302/", "source": "LinkedIn", "title": "Data Analyst - Finance (Remote)", "company": "Hire Feed", "location": "Egypt", "link": "https://www.linkedin.com/jobs/view/4440500302/", "posted": "20 minutes ago", "easy_apply": false, "region": "Egypt", "found_at": "2026-07-14T05:30:29.824941+00:00"}, {"id": "LinkedIn::https://www.linkedin.com/jobs/view/4440394646/", "source": "LinkedIn", "title": "Data Engineer I (Remote)", "company": "Hire Feed", "location": "Egypt", "link": "https://www.linkedin.com/jobs/view/4440394646/", "posted": "13 minutes ago", "easy_apply": false, "region": "Egypt", "found_at": "2026-07-14T05:31:34.939938+00:00"}, {"id": "LinkedIn::https://www.linkedin.com/jobs/view/4440382999/", "source": "LinkedIn", "title": "Expert Opportunity - Business Analyst ($100/hr, up to $2,000/week)", "company": "Ethos", "location": "Dubai, Dubai, United Arab Emirates", "link": "https://www.linkedin.com/jobs/view/4440382999/", "posted": "20 minutes ago", "easy_apply": false, "region": "Remote - United Arab Emirates", "found_at": "2026-07-14T05:37:21.880181+00:00"}, {"id": "LinkedIn::https://www.linkedin.com/jobs/view/4440384856/", "source": "LinkedIn", "title": "Power BI Publisher", "company": "JPS Tech Solutions", "location": "Atlanta, GA", "link": "https://www.linkedin.com/jobs/view/4440384856/", "posted": "46 minutes ago", "easy_apply": false, "region": "Remote - United States", "found_at": "2026-07-14T05:06:35.908309+00:00"}, {"id": "LinkedIn::https://www.linkedin.com/jobs/view/4440382955/", "source": "LinkedIn", "title": "Data Analyst - Business (Remote)", "company": "Hire Feed", "location": "United Arab Emirates", "link": "https://www.linkedin.com/jobs/view/4440382955/", "posted": "11 minutes ago", "easy_apply": false, "region": "Remote - United Arab Emirates", "found_at": "2026-07-14T05:06:55.639761+00:00"}, {"id": "LinkedIn::https://www.linkedin.com/jobs/view/4440393391/", "source": "LinkedIn", "title": "Data Analytics Engineer", "company": "Henkel", "location": "Cairo, Cairo, Egypt", "link": "https://www.linkedin.com/jobs/view/4440393391/", "posted": "8 minutes ago", "easy_apply": false, "region": "Egypt", "found_at": "2026-07-14T04:30:30.148643+00:00"}, {"id": "LinkedIn::https://www.linkedin.com/jobs/view/4440388643/", "source": "LinkedIn", "title": "Data Analyst - Finance (Remote)", "company": "Hire Feed", "location": "United Arab Emirates", "link": "https://www.linkedin.com/jobs/view/4440388643/", "posted": "22 minutes ago", "easy_apply": false, "region": "Remote - United Arab Emirates", "found_at": "2026-07-14T04:37:04.269503+00:00"}, {"id": "LinkedIn::https://www.linkedin.com/jobs/view/4439803485/", "source": "LinkedIn", "title": "Data Engineer", "company": "Robots & Pencils", "location": "Canada, KY", "link": "https://www.linkedin.com/jobs/view/4439803485/", "posted": "56 minutes ago", "easy_apply": false, "region": "Remote - United States", "found_at": "2026-07-14T04:06:59.702333+00:00"}, {"id": "LinkedIn::https://www.linkedin.com/jobs/view/4439431452/", "source": "LinkedIn", "title": "Senior Data Engineer", "company": "MMD Services", "location": "Greater Chicago Area", "link": "https://www.linkedin.com/jobs/view/4439431452/", "posted": "10 hours ago", "easy_apply": false, "region": "Remote - United States", "found_at": "2026-07-14T03:37:06.438875+00:00"}, {"id": "LinkedIn::https://www.linkedin.com/jobs/view/4440365909/", "source": "LinkedIn", "title": "Data Business Analyst", "company": "Regalo Health", "location": "Phoenix, AZ", "link": "https://www.linkedin.com/jobs/view/4440365909/", "posted": "43 minutes ago", "easy_apply": false, "region": "Remote - United States", "found_at": "2026-07-14T02:36:47.252792+00:00"}, {"id": "LinkedIn::https://www.linkedin.com/jobs/view/4437639071/", "source": "LinkedIn", "title": "Research and data analyst", "company": "Bridge", "location": "Dubai, United Arab Emirates", "link": "https://www.linkedin.com/jobs/view/4437639071/", "posted": "25 minutes ago", "easy_apply": false, "region": "Remote - United Arab Emirates", "found_at": "2026-07-14T00:37:16.294008+00:00"}, {"id": "LinkedIn::https://www.linkedin.com/jobs/view/4437238974/", "source": "LinkedIn", "title": "Analytics & Insights Manager", "company": "Procter & Gamble", "location": "Cairo, Cairo, Egypt", "link": "https://www.linkedin.com/jobs/view/4437238974/", "posted": "15 hours ago", "easy_apply": false, "region": "Egypt", "found_at": "2026-07-14T00:00:30.169422+00:00"}, {"id": "LinkedIn::https://www.linkedin.com/jobs/view/4440018311/", "source": "LinkedIn", "title": "Analytics & Insights Manager", "company": "Procter & Gamble Egypt", "location": "Cairo, Cairo, Egypt", "link": "https://www.linkedin.com/jobs/view/4440018311/", "posted": "13 hours ago", "easy_apply": false, "region": "Egypt", "found_at": "2026-07-14T00:00:30.169719+00:00"}, {"id": "LinkedIn::https://www.linkedin.com/jobs/view/4437242566/", "source": "LinkedIn", "title": "Master Data Management Specialist", "company": "MAC for Mobility Manufacturing", "location": "6th of October, Al Jizah, Egypt", "link": "https://www.linkedin.com/jobs/view/4437242566/", "posted": "17 hours ago", "easy_apply": false, "region": "Egypt", "found_at": "2026-07-14T00:00:30.169867+00:00"}, {"id": "LinkedIn::https://www.linkedin.com/jobs/view/4439783534/", "source": "LinkedIn", "title": "Business Intelligence Developer", "company": "TP", "location": "Qesm El Maadi, Cairo, Egypt", "link": "https://www.linkedin.com/jobs/view/4439783534/", "posted": "17 hours ago", "easy_apply": false, "region": "Egypt", "found_at": "2026-07-14T00:00:30.170017+00:00"}, {"id": "LinkedIn::https://www.linkedin.com/jobs/view/4437237976/", "source": "LinkedIn", "title": "Lead / Principal Data Engineer", "company": "Zoolatech", "location": "Egypt", "link": "https://www.linkedin.com/jobs/view/4437237976/", "posted": "16 hours ago", "easy_apply": false, "region": "Egypt", "found_at": "2026-07-14T00:00:30.170168+00:00"}, {"id": "LinkedIn::https://www.linkedin.com/jobs/view/4440032612/", "source": "LinkedIn", "title": "Data Science Lead", "company": "\u062f\u0648\u064a\u0644\u064a\u0648 | Dwelleo", "location": "Egypt", "link": "https://www.linkedin.com/jobs/view/4440032612/", "posted": "10 hours ago", "easy_apply": false, "region": "Egypt", "found_at": "2026-07-14T00:00:30.170312+00:00"}, {"id": "LinkedIn::https://www.linkedin.com/jobs/view/4439456020/", "source": "LinkedIn", "title": "Remote Business Analyst", "company": "Turing", "location": "Egypt", "link": "https://www.linkedin.com/jobs/view/4439456020/", "posted": "5 hours ago", "easy_apply": false, "region": "Egypt", "found_at": "2026-07-14T00:00:39.541946+00:00"}, {"id": "LinkedIn::https://www.linkedin.com/jobs/view/4439456045/", "source": "LinkedIn", "title": "Remote Business Analyst", "company": "Turing", "location": "Egypt", "link": "https://www.linkedin.com/jobs/view/4439456045/", "posted": "5 hours ago", "easy_apply": false, "region": "Egypt", "found_at": "2026-07-14T00:00:39.542097+00:00"}, {"id": "LinkedIn::https://www.linkedin.com/jobs/view/4439435948/", "source": "LinkedIn", "title": "Remote Business Analyst", "company": "Turing", "location": "Egypt", "link": "https://www.linkedin.com/jobs/view/4439435948/", "posted": "5 hours ago", "easy_apply": false, "region": "Egypt", "found_at": "2026-07-14T00:00:39.542247+00:00"}, {"id": "LinkedIn::https://www.linkedin.com/jobs/view/4439450400/", "source": "LinkedIn", "title": "Data Analytics Senior Auditor", "company": "Holcim Latam", "location": "Suez, As Suways, Egypt", "link": "https://www.linkedin.com/jobs/view/4439450400/", "posted": "5 hours ago", "easy_apply": false, "region": "Egypt", "found_at": "2026-07-14T00:00:53.956481+00:00"}, {"id": "LinkedIn::https://www.linkedin.com/jobs/view/4437621291/", "source": "LinkedIn", "title": "Data Analyst", "company": "Haystack", "location": "New York, United States", "link": "https://www.linkedin.com/jobs/view/4437621291/", "posted": "4 hours ago", "easy_apply": false, "region": "Remote - United States", "found_at": "2026-07-14T00:06:36.904020+00:00"}, {"id": "LinkedIn::https://www.linkedin.com/jobs/view/4439194870/", "source": "LinkedIn", "title": "Data Analyst (Excel) | $55/hr Remote", "company": "Crossing Hurdles", "location": "United States", "link": "https://www.linkedin.com/jobs/view/4439194870/", "posted": "11 hours ago", "easy_apply": false, "region": "Remote - United States", "found_at": "2026-07-14T00:06:36.904180+00:00"}, {"id": "LinkedIn::https://www.linkedin.com/jobs/view/4440036428/", "source": "LinkedIn", "title": "Junior Data Analyst", "company": "Helic & Co", "location": "United States", "link": "https://www.linkedin.com/jobs/view/4440036428/", "posted": "10 hours ago", "easy_apply": false, "region": "Remote - United States", "found_at": "2026-07-14T00:06:36.904323+00:00"}, {"id": "LinkedIn::https://www.linkedin.com/jobs/view/4437255130/", "source": "LinkedIn", "title": "Data Analyst", "company": "Haystack", "location": "California, United States", "link": "https://www.linkedin.com/jobs/view/4437255130/", "posted": "16 hours ago", "easy_apply": false, "region": "Remote - United States", "found_at": "2026-07-14T00:06:36.904492+00:00"}, {"id": "LinkedIn::https://www.linkedin.com/jobs/view/4437249622/", "source": "LinkedIn", "title": "Data Analyst", "company": "Haystack", "location": "United States", "link": "https://www.linkedin.com/jobs/view/4437249622/", "posted": "16 hours ago", "easy_apply": false, "region": "Remote - United States", "found_at": "2026-07-14T00:06:36.904639+00:00"}, {"id": "LinkedIn::https://www.linkedin.com/jobs/view/4439460528/", "source": "LinkedIn", "title": "Data Analyst", "company": "KGS Technology Group, Inc", "location": "United States", "link": "https://www.linkedin.com/jobs/view/4439460528/", "posted": "3 hours ago", "easy_apply": false, "region": "Remote - United States", "found_at": "2026-07-14T00:06:36.904784+00:00"}, {"id": "LinkedIn::https://www.linkedin.com/jobs/view/4439460198/", "source": "LinkedIn", "title": "Junior Data Analyst", "company": "Haystack", "location": "Greater Tampa Bay Area", "link": "https://www.linkedin.com/jobs/view/4439460198/", "posted": "4 hours ago", "easy_apply": false, "region": "Remote - United States", "found_at": "2026-07-14T00:06:36.904929+00:00"}, {"id": "LinkedIn::https://www.linkedin.com/jobs/view/4439429953/", "source": "LinkedIn", "title": "Junior Data Analyst", "company": "Matricstek Inc.", "location": "Dallas, TX", "link": "https://www.linkedin.com/jobs/view/4439429953/", "posted": "6 hours ago", "easy_apply": false, "region": "Remote - United States", "found_at": "2026-07-14T00:06:36.905070+00:00"}, {"id": "LinkedIn::https://www.linkedin.com/jobs/view/4437239877/", "source": "LinkedIn", "title": "Data Analyst", "company": "Haystack", "location": "Los Angeles, CA", "link": "https://www.linkedin.com/jobs/view/4437239877/", "posted": "16 hours ago", "easy_apply": false, "region": "Remote - United States", "found_at": "2026-07-14T00:06:36.905212+00:00"}, {"id": "LinkedIn::https://www.linkedin.com/jobs/view/4437614169/", "source": "LinkedIn", "title": "Data Analyst", "company": "Teramind", "location": "United States", "link": "https://www.linkedin.com/jobs/view/4437614169/", "posted": "5 hours ago", "easy_apply": false, "region": "Remote - United States", "found_at": "2026-07-14T00:06:36.905345+00:00"}, {"id": "LinkedIn::https://www.linkedin.com/jobs/view/4439410003/", "source": "LinkedIn", "title": "Business Intelligence Analyst (Excel) | $50/hr Remote", "company": "Crossing Hurdles", "location": "United States", "link": "https://www.linkedin.com/jobs/view/4439410003/", "posted": "11 hours ago", "easy_apply": false, "region": "Remote - United States", "found_at": "2026-07-14T00:06:40.579784+00:00"}, {"id": "LinkedIn::https://www.linkedin.com/jobs/view/4440047251/", "source": "LinkedIn", "title": "Senior Power BI Business Analyst 100% Remote", "company": "HYR Global Source Inc", "location": "United States", "link": "https://www.linkedin.com/jobs/view/4440047251/", "posted": "9 hours ago", "easy_apply": false, "region": "Remote - United States", "found_at": "2026-07-14T00:06:40.579960+00:00"}, {"id": "LinkedIn::https://www.linkedin.com/jobs/view/4439448620/", "source": "LinkedIn", "title": "Business Intelligence Analyst (Power BI) \u2013 Enterprise Data Platform", "company": "Tech One IT", "location": "United States", "link": "https://www.linkedin.com/jobs/view/4439448620/", "posted": "5 hours ago", "easy_apply": false, "region": "Remote - United States", "found_at": "2026-07-14T00:06:40.580114+00:00"}, {"id": "LinkedIn::https://www.linkedin.com/jobs/view/4439477221/", "source": "LinkedIn", "title": "Business Intelligence Analyst", "company": "Insight Global", "location": "Memphis Metropolitan Area", "link": "https://www.linkedin.com/jobs/view/4439477221/", "posted": "2 hours ago", "easy_apply": false, "region": "Remote - United States", "found_at": "2026-07-14T00:06:40.580259+00:00"}, {"id": "LinkedIn::https://www.linkedin.com/jobs/view/4440005820/", "source": "LinkedIn", "title": "Data & BI Analyst", "company": "Sundayy", "location": "United States", "link": "https://www.linkedin.com/jobs/view/4440005820/", "posted": "12 hours ago", "easy_apply": false, "region": "Remote - United States", "found_at": "2026-07-14T00:06:40.580419+00:00"}, {"id": "LinkedIn::https://www.linkedin.com/jobs/view/4437603972/", "source": "LinkedIn", "title": "Entry Level Business Intelligence Developer", "company": "Optimum Healthcare IT", "location": "United States", "link": "https://www.linkedin.com/jobs/view/4437603972/", "posted": "3 hours ago", "easy_apply": false, "region": "Remote - United States", "found_at": "2026-07-14T00:06:40.580575+00:00"}, {"id": "LinkedIn::https://www.linkedin.com/jobs/view/4439438007/", "source": "LinkedIn", "title": "Sr. Strategic Intelligence & Business Analytics Manager", "company": "Jobgether", "location": "United States", "link": "https://www.linkedin.com/jobs/view/4439438007/", "posted": "8 hours ago", "easy_apply": false, "region": "Remote - United States", "found_at": "2026-07-14T00:06:40.580717+00:00"}, {"id": "LinkedIn::https://www.linkedin.com/jobs/view/4440055135/", "source": "LinkedIn", "title": "BI (Cogito) Developer- REMOTE CONTRACT!", "company": "Talent Groups", "location": "United States", "link": "https://www.linkedin.com/jobs/view/4440055135/", "posted": "9 hours ago", "easy_apply": false, "region": "Remote - United States", "found_at": "2026-07-14T00:06:40.580861+00:00"}, {"id": "LinkedIn::https://www.linkedin.com/jobs/view/4437615656/", "source": "LinkedIn", "title": "Senior Business Intelligence Data Analyst", "company": "Gainwell Technologies", "location": "Texas, United States", "link": "https://www.linkedin.com/jobs/view/4437615656/", "posted": "3 hours ago", "easy_apply": false, "region": "Remote - United States", "found_at": "2026-07-14T00:06:40.581007+00:00"}, {"id": "LinkedIn::https://www.linkedin.com/jobs/view/4439413543/", "source": "LinkedIn", "title": "SQL Business Analyst", "company": "Lorven Technologies Inc.", "location": "United States", "link": "https://www.linkedin.com/jobs/view/4439413543/", "posted": "9 hours ago", "easy_apply": false, "region": "Remote - United States", "found_at": "2026-07-14T00:06:40.581152+00:00"}, {"id": "LinkedIn::https://www.linkedin.com/jobs/view/4437601885/", "source": "LinkedIn", "title": "Business Intelligence Developer", "company": "Packsize", "location": "Utah, United States", "link": "https://www.linkedin.com/jobs/view/4437601885/", "posted": "5 hours ago", "easy_apply": false, "region": "Remote - United States", "found_at": "2026-07-14T00:06:42.909727+00:00"}, {"id": "LinkedIn::https://www.linkedin.com/jobs/view/4439421424/", "source": "LinkedIn", "title": "Power BI Developer", "company": "Delta System & Software, Inc.", "location": "United States", "link": "https://www.linkedin.com/jobs/view/4439421424/", "posted": "9 hours ago", "easy_apply": false, "region": "Remote - United States", "found_at": "2026-07-14T00:06:46.315518+00:00"}, {"id": "LinkedIn::https://www.linkedin.com/jobs/view/4439402623/", "source": "LinkedIn", "title": "Data Analyst", "company": "AARATECH", "location": "United States", "link": "https://www.linkedin.com/jobs/view/4439402623/", "posted": "10 hours ago", "easy_apply": false, "region": "Remote - United States", "found_at": "2026-07-14T00:06:46.316328+00:00"}, {"id": "LinkedIn::https://www.linkedin.com/jobs/view/4439431160/", "source": "LinkedIn", "title": "Junior Data Analyst - M&A / Private Equity", "company": "RingStone", "location": "Austin, Texas Metropolitan Area", "link": "https://www.linkedin.com/jobs/view/4439431160/", "posted": "6 hours ago", "easy_apply": false, "region": "Remote - United States", "found_at": "2026-07-14T00:06:46.316493+00:00"}, {"id": "LinkedIn::https://www.linkedin.com/jobs/view/4439429464/", "source": "LinkedIn", "title": "Financial Reporting Analyst", "company": "Horizon Bank", "location": "United States", "link": "https://www.linkedin.com/jobs/view/4439429464/", "posted": "7 hours ago", "easy_apply": false, "region": "Remote - United States", "found_at": "2026-07-14T00:06:48.491609+00:00"}, {"id": "LinkedIn::https://www.linkedin.com/jobs/view/4113908411/", "source": "LinkedIn", "title": "Senior Consultant - Reporting Analyst - Remote", "company": "Nordic Global", "location": "United States", "link": "https://www.linkedin.com/jobs/view/4113908411/", "posted": "14 hours ago", "easy_apply": false, "region": "Remote - United States", "found_at": "2026-07-14T00:06:48.492072+00:00"}, {"id": "LinkedIn::https://www.linkedin.com/jobs/view/4421850585/", "source": "LinkedIn", "title": "Fraud Reporting Analyst", "company": "Pathward", "location": "United States", "link": "https://www.linkedin.com/jobs/view/4421850585/", "posted": "5 hours ago", "easy_apply": false, "region": "Remote - United States", "found_at": "2026-07-14T00:06:48.492217+00:00"}, {"id": "LinkedIn::https://www.linkedin.com/jobs/view/4440070186/", "source": "LinkedIn", "title": "Business Analyst", "company": "Aditi Consulting", "location": "Texas, United States", "link": "https://www.linkedin.com/jobs/view/4440070186/", "posted": "7 hours ago", "easy_apply": false, "region": "Remote - United States", "found_at": "2026-07-14T00:06:48.492378+00:00"}, {"id": "LinkedIn::https://www.linkedin.com/jobs/view/4439448596/", "source": "LinkedIn", "title": "Business Analyst", "company": "Fracto Solutions", "location": "United States", "link": "https://www.linkedin.com/jobs/view/4439448596/", "posted": "5 hours ago", "easy_apply": false, "region": "Remote - United States", "found_at": "2026-07-14T00:06:48.492519+00:00"}, {"id": "LinkedIn::https://www.linkedin.com/jobs/view/4437287553/", "source": "LinkedIn", "title": "Business Analyst", "company": "AS Technology Corporation", "location": "New Jersey, United States", "link": "https://www.linkedin.com/jobs/view/4437287553/", "posted": "8 hours ago", "easy_apply": false, "region": "Remote - United States", "found_at": "2026-07-14T00:06:48.492664+00:00"}, {"id": "LinkedIn::https://www.linkedin.com/jobs/view/4439404386/", "source": "LinkedIn", "title": "Business Analyst", "company": "AARATECH", "location": "United States", "link": "https://www.linkedin.com/jobs/view/4439404386/", "posted": "11 hours ago", "easy_apply": false, "region": "Remote - United States", "found_at": "2026-07-14T00:06:48.492798+00:00"}, {"id": "LinkedIn::https://www.linkedin.com/jobs/view/4440051918/", "source": "LinkedIn", "title": "Business Analyst IV (6238)", "company": "itD", "location": "United States", "link": "https://www.linkedin.com/jobs/view/4440051918/", "posted": "6 hours ago", "easy_apply": false, "region": "Remote - United States", "found_at": "2026-07-14T00:06:48.492943+00:00"}, {"id": "LinkedIn::https://www.linkedin.com/jobs/view/4439776794/", "source": "LinkedIn", "title": "Data Engineer", "company": "Robots & Pencils", "location": "Seattle, WA", "link": "https://www.linkedin.com/jobs/view/4439776794/", "posted": "19 hours ago", "easy_apply": false, "region": "Remote - United States", "found_at": "2026-07-14T00:06:51.946757+00:00"}, {"id": "LinkedIn::https://www.linkedin.com/jobs/view/4432125298/", "source": "LinkedIn", "title": "Data Engineer I", "company": "Flashpoint", "location": "United States", "link": "https://www.linkedin.com/jobs/view/4432125298/", "posted": "56 minutes ago", "easy_apply": false, "region": "Remote - United States", "found_at": "2026-07-14T00:06:51.946922+00:00"}, {"id": "LinkedIn::https://www.linkedin.com/jobs/view/4439449436/", "source": "LinkedIn", "title": "Senior Research Data Engineer (US)", "company": "PointClickCare", "location": "United States", "link": "https://www.linkedin.com/jobs/view/4439449436/", "posted": "5 hours ago", "easy_apply": false, "region": "Remote - United States", "found_at": "2026-07-14T00:06:51.947063+00:00"}, {"id": "LinkedIn::https://www.linkedin.com/jobs/view/4439404622/", "source": "LinkedIn", "title": "Data Engineer", "company": "Relativix", "location": "Austin, Texas Metropolitan Area", "link": "https://www.linkedin.com/jobs/view/4439404622/", "posted": "9 hours ago", "easy_apply": false, "region": "Remote - United States", "found_at": "2026-07-14T00:06:51.947203+00:00"}, {"id": "LinkedIn::https://www.linkedin.com/jobs/view/3970353535/", "source": "LinkedIn", "title": "Data Engineer", "company": "Figma", "location": "San Francisco, CA", "link": "https://www.linkedin.com/jobs/view/3970353535/", "posted": "10 hours ago", "easy_apply": false, "region": "Remote - United States", "found_at": "2026-07-14T00:06:51.947348+00:00"}, {"id": "LinkedIn::https://www.linkedin.com/jobs/view/4440319362/", "source": "LinkedIn", "title": "Junior Data Engineer", "company": "Capital Technology Group", "location": "Washington, DC", "link": "https://www.linkedin.com/jobs/view/4440319362/", "posted": "3 hours ago", "easy_apply": false, "region": "Remote - United States", "found_at": "2026-07-14T00:06:51.947506+00:00"}, {"id": "LinkedIn::https://www.linkedin.com/jobs/view/4440039659/", "source": "LinkedIn", "title": "Data Engineer", "company": "Largeton Group", "location": "United States", "link": "https://www.linkedin.com/jobs/view/4440039659/", "posted": "9 hours ago", "easy_apply": false, "region": "Remote - United States", "found_at": "2026-07-14T00:06:51.947750+00:00"}, {"id": "LinkedIn::https://www.linkedin.com/jobs/view/4438842830/", "source": "LinkedIn", "title": "Marketing Analytics Engineer", "company": "New York Technology Partners", "location": "United States", "link": "https://www.linkedin.com/jobs/view/4438842830/", "posted": "4 hours ago", "easy_apply": false, "region": "Remote - United States", "found_at": "2026-07-14T00:06:51.947896+00:00"}, {"id": "LinkedIn::https://www.linkedin.com/jobs/view/4439127748/", "source": "LinkedIn", "title": "Senior Data Engineer", "company": "Jobgether", "location": "United States", "link": "https://www.linkedin.com/jobs/view/4439127748/", "posted": "17 hours ago", "easy_apply": false, "region": "Remote - United States", "found_at": "2026-07-14T00:06:51.948033+00:00"}, {"id": "LinkedIn::https://www.linkedin.com/jobs/view/4439188966/", "source": "LinkedIn", "title": "Data Analyst (Product)", "company": "Revolut", "location": "United Arab Emirates", "link": "https://www.linkedin.com/jobs/view/4439188966/", "posted": "11 hours ago", "easy_apply": false, "region": "Remote - United Arab Emirates", "found_at": "2026-07-14T00:07:07.555722+00:00"}, {"id": "LinkedIn::https://www.linkedin.com/jobs/view/4439774812/", "source": "LinkedIn", "title": "Excel Analyst (Remote)", "company": "Quik Hire Staffing", "location": "United Arab Emirates", "link": "https://www.linkedin.com/jobs/view/4439774812/", "posted": "19 hours ago", "easy_apply": false, "region": "Remote - United Arab Emirates", "found_at": "2026-07-14T00:07:07.555878+00:00"}, {"id": "LinkedIn::https://www.linkedin.com/jobs/view/4439792090/", "source": "LinkedIn", "title": "Data Analyst - Business (Remote)", "company": "Hire Feed", "location": "United Arab Emirates", "link": "https://www.linkedin.com/jobs/view/4439792090/", "posted": "19 hours ago", "easy_apply": false, "region": "Remote - United Arab Emirates", "found_at": "2026-07-14T00:07:07.556019+00:00"}, {"id": "LinkedIn::https://www.linkedin.com/jobs/view/4439794009/", "source": "LinkedIn", "title": "Data Analyst - Finance (Remote)", "company": "Hire Feed", "location": "United Arab Emirates", "link": "https://www.linkedin.com/jobs/view/4439794009/", "posted": "19 hours ago", "easy_apply": false, "region": "Remote - United Arab Emirates", "found_at": "2026-07-14T00:07:07.556159+00:00"}, {"id": "LinkedIn::https://www.linkedin.com/jobs/view/4439784289/", "source": "LinkedIn", "title": "Business Intelligence Consultant (Remote)", "company": "Quik Hire Staffing", "location": "United Arab Emirates", "link": "https://www.linkedin.com/jobs/view/4439784289/", "posted": "19 hours ago", "easy_apply": false, "region": "Remote - United Arab Emirates", "found_at": "2026-07-14T00:07:09.763782+00:00"}]}